[
  {
    "depot": "Akkalkot via Radhanagari",
    "departureTimes": [
      "16:00"
    ],
    "via": [
      "Akkalkot",
      "Radhanagari",
      "Mhapsa",
      "Banda",
      "Sawantwadi",
      "Kudal",
      "Oros",
      "Kankavali",
      "Phonda",
      "Sangola",
      "Pandharpur",
      "Solapur"
    ]
  },
  {
    "depot": "Belgaon / Belgaum",
    "departureTimes": [
      "07:00",
      "10:30"
    ],
    "via": []
  },
  {
    "depot": "Devgad",
    "departureTimes": [
      "06:45",
      "13:30"
    ],
    "via": [
      "Mapusa",
      "Thivim",
      "Assnora",
      "Mulgao",
      "Dodamarg",
      "Banda",
      "Sawantwadi",
      "Kudal",
      "Kankavali",
      "Nandgaon",
      "Jamsande"
    ]
  },
  {
    "depot": "Dharashiv via Radhanagari (Osmanabad)",
    "departureTimes": [
      "17:30"
    ],
    "via": [
      "Dharashiv",
      "Radhanagari Osmanabad",
      "Doda Marg",
      "Sawantwadi",
      "Pandharpur",
      "Solapur",
      "Tuljapur"
    ]
  },
  {
    "depot": "Kolhapur",
    "departureTimes": [
      "08:00",
      "13:45",
      "09:30",
      "15:30"
    ],
    "via": [
      "Mhapsa",
      "Dodamarg"
    ]
  },
  {
    "depot": "Kudal",
    "departureTimes": [
      "06:45",
      "09:25",
      "11:30",
      "17:50"
    ],
    "via": []
  },
  {
    "depot": "Mahabaleshwar",
    "departureTimes": [
      "05:30"
    ],
    "via": [
      "Gaganbawada"
    ]
  },
  {
    "depot": "Malvan",
    "departureTimes": [
      "13:00"
    ],
    "via": [
      "Sawantwadi"
    ]
  },
  {
    "depot": "Pune via Gaganbawda",
    "departureTimes": [
      "06:00",
      "10:00",
      "13:45",
      "17:00",
      "18:00"
    ],
    "via": [
      "Pune",
      "Gaganbawda",
      "Mhapsa",
      "Banda",
      "Sawantwadi",
      "Kudal",
      "Oros",
      "Kankavali",
      "Swargate",
      "Pune Railway"
    ]
  },
  {
    "depot": "Pune via Radhanagari",
    "departureTimes": [
      "07:30",
      "21:00"
    ],
    "via": [
      "Pune",
      "Radhanagari",
      "Mhapsa",
      "Banda",
      "Sawantwadi",
      "Kudal",
      "Oros",
      "Kankavali",
      "Katraj",
      "Swargate",
      "Pune Railway"
    ]
  },
  {
    "depot": "Radhanagari",
    "departureTimes": [
      "07:15"
    ],
    "via": [
      "Chandgad",
      "Gadhinglaj"
    ]
  },
  {
    "depot": "Sawantwadi",
    "departureTimes": [
      "08:45",
      "10:15",
      "11:00",
      "12:15",
      "14:30",
      "15:45",
      "16:45",
      "19:00"
    ],
    "via": []
  },
  {
    "depot": "Tasgaon",
    "departureTimes": [
      "08:30"
    ],
    "via": [
      "Mapusa",
      "Banda",
      "Sawantwadi",
      "Kolhapur",
      "Sangli"
    ]
  },
  {
    "depot": "Vengurla",
    "departureTimes": [
      "09:15",
      "10:45",
      "12:00",
      "14:00",
      "17:15"
    ],
    "via": []
  },
  {
    "depot": "Vijaydurg",
    "departureTimes": [
      "14:15"
    ],
    "via": [
      "Patradevi"
    ]
  }
]